scrapy_toolbox/__init__.py
scrapy_toolbox/command_line.py
scrapy_toolbox/database.py
scrapy_toolbox/error_handling.py
scrapy_toolbox/error_processing.py
scrapy_toolbox/mapper.py
scrapy_toolbox-0.3.5.dist-info/licenses/LICENSE
scrapy_toolbox-0.3.5.dist-info/METADATA
scrapy_toolbox-0.3.5.dist-info/WHEEL
scrapy_toolbox-0.3.5.dist-info/entry_points.txt
scrapy_toolbox-0.3.5.dist-info/top_level.txt
scrapy_toolbox-0.3.5.dist-info/RECORD
