Metadata-Version: 2.4
Name: scrapy-toolbox
Version: 0.3.5
Summary: Error Handling and Processing for your Scrapy Exceptions
Home-page: https://github.com/janwendt/scrapy-toolbox
Download-URL: https://github.com/janwendt/scrapy-toolbox/archive/0.3.5.tar.gz
Author: Jan Wendt
Classifier: Programming Language :: Python :: 3
Classifier: License :: OSI Approved :: MIT License
Classifier: Operating System :: OS Independent
Requires-Python: >=3.6
License-File: LICENSE
Requires-Dist: scrapy
Requires-Dist: sqlalchemy
Requires-Dist: sqlalchemy_utils
Requires-Dist: gitpython
Requires-Dist: pygithub
Requires-Dist: pymysql
Requires-Dist: psycopg2
Dynamic: author
Dynamic: classifier
Dynamic: description
Dynamic: description-content-type
Dynamic: download-url
Dynamic: home-page
Dynamic: license-file
Dynamic: requires-dist
Dynamic: requires-python
Dynamic: summary
